link_all/__init__.py
link_all/apps.py
link_all/cms_plugins.py
link_all/dataclasses.py
link_all/middleware.py
link_all/models.py
link_all/receivers.py
link_all/settings.py
link_all/api/__init__.py
link_all/api/urls.py
link_all/api/views.py
link_all/migrations/0001_initial.py
link_all/migrations/0002_add_field_link_label.py
link_all/migrations/0003_rename_field_link_type.py
link_all/migrations/0004_add_field_link_type.py
link_all/migrations/0005_add_button_model.py
link_all/migrations/0006_alter_fields_for_button_mixin.py
link_all/migrations/0007_alter_field_make_button_color_optional.py
link_all/migrations/__init__.py
link_all/static/link_all/babel.config.js
link_all/static/link_all/vue.config.js
link_all/static/link_all/dist/app.css
link_all/static/link_all/dist/app.js
link_all/static/link_all/dist/app.js.map
link_all/static/link_all/dist/chunk-vendors.css
link_all/static/link_all/dist/chunk-vendors.js
link_all/static/link_all/dist/chunk-vendors.js.map
link_all/static/link_all/dist/index.html
link_all/static/link_all/src/link-all.html
link_all/static/link_all/src/link-all.ts
link_all/static/link_all/src/link_all.vue
link_all/static/link_all/src/main.ts
link_all/static/link_all/src/shims-tsx.d.ts
link_all/static/link_all/src/shims-vue.d.ts
link_all/static/link_all/src/services/django.ts
link_all/templates/link_all/link_all.html
link_all/templates/link_all/link_all_button.html
link_all/templates/link_all/admin/link_all.html
djangocms_link_all-0.6.1.2.dist-info/METADATA
djangocms_link_all-0.6.1.2.dist-info/WHEEL
djangocms_link_all-0.6.1.2.dist-info/top_level.txt
djangocms_link_all-0.6.1.2.dist-info/RECORD
