Metadata-Version: 2.1
Name: djangocms-link-all
Version: 0.6.1.2
Summary: UNKNOWN
Home-page: https://gitlab.com/what-digital/djangocms-link-all
Author: Victor Yunenko
Author-email: victor@what.digital
License: UNKNOWN
Platform: UNKNOWN
Requires-Python: >= 3.7
Requires-Dist: django (<4,>=2.2)
Requires-Dist: django-cms (<4,>=3.7)
Requires-Dist: django-filer
Requires-Dist: jsons
